peppr/__init__.py
peppr/bisyrmsd.py
peppr/bounds.py
peppr/charge.py
peppr/clashes.py
peppr/cli.py
peppr/common.py
peppr/contacts.py
peppr/dockq.py
peppr/evaluator.py
peppr/match.py
peppr/metric.py
peppr/protonation.csv
peppr/py.typed
peppr/rotamer.py
peppr/sanitize.py
peppr/selector.py
peppr/version.py
peppr/volume.py
peppr-0.12.0.dist-info/METADATA
peppr-0.12.0.dist-info/WHEEL
peppr-0.12.0.dist-info/entry_points.txt
peppr-0.12.0.dist-info/licenses/LICENSE.txt
peppr-0.12.0.dist-info/RECORD
